opentelemetry/distro/__init__.py
opentelemetry/distro/py.typed
opentelemetry/distro/version.py
tapm_distro-0.55.4.dist-info/METADATA
tapm_distro-0.55.4.dist-info/WHEEL
tapm_distro-0.55.4.dist-info/entry_points.txt
tapm_distro-0.55.4.dist-info/RECORD
