Metadata-Version: 2.4
Name: tapm-distro
Version: 0.55.4
Summary: TAPM Python Distro
Project-URL: Homepage, https://github.com/open-telemetry/opentelemetry-python-contrib/tree/main/opentelemetry-distro
Project-URL: Repository, https://github.com/open-telemetry/opentelemetry-python-contrib
Author-email: OpenTelemetry Authors <cncf-opentelemetry-contributors@lists.cncf.io>
License-Expression: Apache-2.0
Classifier: Development Status :: 4 - Beta
Classifier: Intended Audience :: Developers
Classifier: License :: OSI Approved :: Apache Software License
Classifier: Programming Language :: Python
Classifier: Programming Language :: Python :: 3
Classifier: Programming Language :: Python :: 3.8
Classifier: Programming Language :: Python :: 3.9
Classifier: Programming Language :: Python :: 3.10
Classifier: Programming Language :: Python :: 3.11
Classifier: Programming Language :: Python :: 3.12
Classifier: Programming Language :: Python :: 3.13
Classifier: Typing :: Typed
Requires-Python: >=3.8
Requires-Dist: opentelemetry-api~=1.12
Requires-Dist: opentelemetry-sdk~=1.13
Requires-Dist: tapm-instrumentation==0.55.4
Provides-Extra: otlp
Requires-Dist: opentelemetry-exporter-otlp==1.34.0.dev; extra == 'otlp'
